odoo/addons/mass_mailing_newsletter_welcome_mail/README.rst
odoo/addons/mass_mailing_newsletter_welcome_mail/__init__.py
odoo/addons/mass_mailing_newsletter_welcome_mail/__manifest__.py
odoo/addons/mass_mailing_newsletter_welcome_mail/controllers/__init__.py
odoo/addons/mass_mailing_newsletter_welcome_mail/controllers/main.py
odoo/addons/mass_mailing_newsletter_welcome_mail/data/mail_template.xml
odoo/addons/mass_mailing_newsletter_welcome_mail/i18n/es.po
odoo/addons/mass_mailing_newsletter_welcome_mail/i18n/mass_mailing_newsletter_welcome_mail.pot
odoo/addons/mass_mailing_newsletter_welcome_mail/i18n/mass_mailing_welcome_mail.pot
odoo/addons/mass_mailing_newsletter_welcome_mail/i18n/pt.po
odoo/addons/mass_mailing_newsletter_welcome_mail/models/__init__.py
odoo/addons/mass_mailing_newsletter_welcome_mail/models/mail_mass_mailing_list.py
odoo/addons/mass_mailing_newsletter_welcome_mail/readme/CONFIGURE.rst
odoo/addons/mass_mailing_newsletter_welcome_mail/readme/CONTRIBUTORS.rst
odoo/addons/mass_mailing_newsletter_welcome_mail/readme/DESCRIPTION.rst
odoo/addons/mass_mailing_newsletter_welcome_mail/readme/ROADMAP.rst
odoo/addons/mass_mailing_newsletter_welcome_mail/readme/USAGE.rst
odoo/addons/mass_mailing_newsletter_welcome_mail/static/description/icon.png
odoo/addons/mass_mailing_newsletter_welcome_mail/static/description/index.html
odoo/addons/mass_mailing_newsletter_welcome_mail/views/mail_mass_mailing_list.xml
odoo12_addon_mass_mailing_newsletter_welcome_mail-12.0.1.0.0.99.dev6.dist-info/METADATA
odoo12_addon_mass_mailing_newsletter_welcome_mail-12.0.1.0.0.99.dev6.dist-info/WHEEL
odoo12_addon_mass_mailing_newsletter_welcome_mail-12.0.1.0.0.99.dev6.dist-info/top_level.txt
odoo12_addon_mass_mailing_newsletter_welcome_mail-12.0.1.0.0.99.dev6.dist-info/RECORD
